[{"name":"Rubic","description":"rubic cube","imageUrl":"https://images-na.ssl-images-amazon.com/images/I/81dIEAgoytL._AC_SL1500_.jpg","difficultyLevel":"3","id":"11vajc0knpu2srs"},{"name":"Triangle rubic","description":"Triangle rubic cube","imageUrl":"https://encrypted-tbn0.gstatic.com/images?q=tbn:ANd9GcQ5MywQDNoJddS-qfoY5SgaKjTvYyRaxJafcg&usqp=CAU","difficultyLevel":"4","id":"11vahdwknpu5eof"},{"name":"Mirror Cube","description":"Interesting Mirror Cube","imageUrl":"https://logicbg.com/wp-content/uploads/2019/04/rubik-kub-Mirror-Cube-silver-ogledalen-kub-podreden.jpg","difficultyLevel":"3","id":"11va6koknyfzzcu"}]